LICENCE
MANIFEST.in
README.rst
setup.cfg
setup.py
bambuinformasaun.egg-info/PKG-INFO
bambuinformasaun.egg-info/SOURCES.txt
bambuinformasaun.egg-info/dependency_links.txt
bambuinformasaun.egg-info/requires.txt
bambuinformasaun.egg-info/top_level.txt
informasaun/__init__.py
informasaun/admin.py
informasaun/apps.py
informasaun/forms.py
informasaun/models.py
informasaun/tests.py
informasaun/urls.py
informasaun/utils.py
informasaun/views.py
informasaun/migrations/0001_initial.py
informasaun/migrations/0002_alter_konteuduprodutu_data_produsaun_and_more.py
informasaun/migrations/0003_anunsiu_imagenanunsiu_konteuduimagenanunsiu_and_more.py
informasaun/migrations/0004_kategoriainformasaun_and_more.py
informasaun/migrations/0005_fileanunsiu_and_more.py
informasaun/migrations/0006_alter_fileanunsiu_user_created.py
informasaun/migrations/0007_fileanunsiu_titulu.py
informasaun/migrations/__init__.py
informasaun/templates/informasaun/anunsiu/detallu copy.html
informasaun/templates/informasaun/anunsiu/detallu.html
informasaun/templates/informasaun/anunsiu/detallupublika.html
informasaun/templates/informasaun/anunsiu/django.code-workspace
informasaun/templates/informasaun/anunsiu/input.html
informasaun/templates/informasaun/anunsiu/inputkonteuduanunsiu.html
informasaun/templates/informasaun/anunsiu/inputkonteuduperfil.html
informasaun/templates/informasaun/anunsiu/lista.html
informasaun/templates/informasaun/anunsiu/maneza_konteudu.html
informasaun/templates/informasaun/anunsiu/manezakonteudu.html
informasaun/templates/informasaun/anunsiu/update copy.html
informasaun/templates/informasaun/anunsiu/update.html
informasaun/templates/informasaun/informasaun/detallu copy.html
informasaun/templates/informasaun/informasaun/detallu.html
informasaun/templates/informasaun/informasaun/detallupublika.html
informasaun/templates/informasaun/informasaun/django.code-workspace
informasaun/templates/informasaun/informasaun/input.html
informasaun/templates/informasaun/informasaun/inputkonteuduinformasaun.html
informasaun/templates/informasaun/informasaun/inputkonteuduperfil.html
informasaun/templates/informasaun/informasaun/lista.html
